volundr/__init__.py
volundr/volundr.py
volundr-0.0.1.dist-info/LICENSE
volundr-0.0.1.dist-info/METADATA
volundr-0.0.1.dist-info/WHEEL
volundr-0.0.1.dist-info/top_level.txt
volundr-0.0.1.dist-info/RECORD
