Metadata-Version: 2.1
Name: volundr
Version: 0.0.1
Summary: Volundr
Home-page: UNKNOWN
Author: nischkar
Author-email: mail@nischkar.com
License: UNKNOWN
Platform: UNKNOWN
Classifier: Programming Language :: Python :: 3
Classifier: License :: OSI Approved :: MIT License
Classifier: Operating System :: OS Independent
Requires-Python: >=3.6
License-File: LICENSE
